{
  "node": "Button/SB first decision, preflop, 100 BB effective",
  "modelFile": "public/models/holdem_strategy.onnx",
  "generatedBy": "solver/scripts/gen_landing_grid.py",
  "actions": ["f", "c", "b0", "b1", "a"],
  "aggregate": [0.2463, 0.4618, 0.127, 0.0797, 0.0853],
  "cells": [
    {
      "label": "AA",
      "probs": [0.0178, 0.2134, 0.0867, 0.1926, 0.4895]
    },
    {
      "label": "AKs",
      "probs": [0.0, 0.2478, 0.1579, 0.2147, 0.3796]
    },
    {
      "label": "AQs",
      "probs": [0.0, 0.3027, 0.2308, 0.2016, 0.2649]
    },
    {
      "label": "AJs",
      "probs": [0.0, 0.3349, 0.1923, 0.1556, 0.3172]
    },
    {
      "label": "ATs",
      "probs": [0.0, 0.2745, 0.256, 0.1713, 0.2983]
    },
    {
      "label": "A9s",
      "probs": [0.0, 0.2965, 0.2901, 0.1605, 0.253]
    },
    {
      "label": "A8s",
      "probs": [0.0, 0.3748, 0.2468, 0.1519, 0.2265]
    },
    {
      "label": "A7s",
      "probs": [0.0, 0.341, 0.2511, 0.1503, 0.2575]
    },
    {
      "label": "A6s",
      "probs": [0.0, 0.2915, 0.1989, 0.1813, 0.3282]
    },
    {
      "label": "A5s",
      "probs": [0.0, 0.3371, 0.1641, 0.1837, 0.3151]
    },
    {
      "label": "A4s",
      "probs": [0.0, 0.2948, 0.1737, 0.2066, 0.3249]
    },
    {
      "label": "A3s",
      "probs": [0.0082, 0.3968, 0.1825, 0.157, 0.2555]
    },
    {
      "label": "A2s",
      "probs": [0.0076, 0.4133, 0.1761, 0.16, 0.243]
    },
    {
      "label": "AKo",
      "probs": [0.0119, 0.1682, 0.1259, 0.2518, 0.4422]
    },
    {
      "label": "KK",
      "probs": [0.0135, 0.2099, 0.1713, 0.247, 0.3584]
    },
    {
      "label": "KQs",
      "probs": [0.0218, 0.3502, 0.2676, 0.1949, 0.1655]
    },
    {
      "label": "KJs",
      "probs": [0.02, 0.3776, 0.2404, 0.1675, 0.1946]
    },
    {
      "label": "KTs",
      "probs": [0.0269, 0.3483, 0.2799, 0.1656, 0.1792]
    },
    {
      "label": "K9s",
      "probs": [0.0341, 0.437, 0.2635, 0.1447, 0.1208]
    },
    {
      "label": "K8s",
      "probs": [0.0356, 0.4787, 0.2341, 0.1326, 0.119]
    },
    {
      "label": "K7s",
      "probs": [0.0419, 0.4419, 0.257, 0.135, 0.1242]
    },
    {
      "label": "K6s",
      "probs": [0.0286, 0.4411, 0.2415, 0.1524, 0.1364]
    },
    {
      "label": "K5s",
      "probs": [0.0497, 0.4119, 0.2134, 0.166, 0.1591]
    },
    {
      "label": "K4s",
      "probs": [0.036, 0.4371, 0.1922, 0.1741, 0.1606]
    },
    {
      "label": "K3s",
      "probs": [0.0626, 0.4956, 0.1993, 0.1263, 0.1162]
    },
    {
      "label": "K2s",
      "probs": [0.0692, 0.5298, 0.183, 0.1181, 0.0999]
    },
    {
      "label": "AQo",
      "probs": [0.0016, 0.2245, 0.1834, 0.2257, 0.3649]
    },
    {
      "label": "KQo",
      "probs": [0.0165, 0.2597, 0.2621, 0.2275, 0.2342]
    },
    {
      "label": "QQ",
      "probs": [0.0354, 0.3245, 0.281, 0.1954, 0.1637]
    },
    {
      "label": "QJs",
      "probs": [0.0608, 0.4165, 0.2512, 0.1441, 0.1274]
    },
    {
      "label": "QTs",
      "probs": [0.0703, 0.4245, 0.254, 0.1328, 0.1184]
    },
    {
      "label": "Q9s",
      "probs": [0.1106, 0.4642, 0.233, 0.1052, 0.087]
    },
    {
      "label": "Q8s",
      "probs": [0.1001, 0.4884, 0.2085, 0.11, 0.0929]
    },
    {
      "label": "Q7s",
      "probs": [0.0919, 0.4695, 0.233, 0.1096, 0.0961]
    },
    {
      "label": "Q6s",
      "probs": [0.1064, 0.4874, 0.2086, 0.1114, 0.0862]
    },
    {
      "label": "Q5s",
      "probs": [0.1715, 0.4891, 0.1782, 0.0826, 0.0786]
    },
    {
      "label": "Q4s",
      "probs": [0.1542, 0.4946, 0.1704, 0.0972, 0.0836]
    },
    {
      "label": "Q3s",
      "probs": [0.2049, 0.4689, 0.1594, 0.0823, 0.0845]
    },
    {
      "label": "Q2s",
      "probs": [0.2205, 0.4885, 0.1474, 0.0718, 0.0718]
    },
    {
      "label": "AJo",
      "probs": [0.0, 0.348, 0.1726, 0.1682, 0.3112]
    },
    {
      "label": "KJo",
      "probs": [0.0135, 0.4208, 0.2491, 0.1636, 0.1531]
    },
    {
      "label": "QJo",
      "probs": [0.0849, 0.5166, 0.2118, 0.1022, 0.0847]
    },
    {
      "label": "JJ",
      "probs": [0.0507, 0.5231, 0.1918, 0.1247, 0.1097]
    },
    {
      "label": "JTs",
      "probs": [0.044, 0.3974, 0.2737, 0.1487, 0.1362]
    },
    {
      "label": "J9s",
      "probs": [0.0738, 0.5173, 0.2155, 0.1081, 0.0852]
    },
    {
      "label": "J8s",
      "probs": [0.0768, 0.5266, 0.1905, 0.1101, 0.096]
    },
    {
      "label": "J7s",
      "probs": [0.0924, 0.5319, 0.1985, 0.0949, 0.0822]
    },
    {
      "label": "J6s",
      "probs": [0.0859, 0.5378, 0.186, 0.1084, 0.0818]
    },
    {
      "label": "J5s",
      "probs": [0.1524, 0.5038, 0.1601, 0.0933, 0.0904]
    },
    {
      "label": "J4s",
      "probs": [0.1231, 0.528, 0.1582, 0.1026, 0.0882]
    },
    {
      "label": "J3s",
      "probs": [0.1914, 0.5232, 0.1277, 0.0767, 0.081]
    },
    {
      "label": "J2s",
      "probs": [0.2374, 0.5332, 0.1141, 0.0602, 0.0552]
    },
    {
      "label": "ATo",
      "probs": [0.0, 0.3578, 0.217, 0.1671, 0.2581]
    },
    {
      "label": "KTo",
      "probs": [0.0326, 0.4787, 0.2475, 0.1353, 0.1059]
    },
    {
      "label": "QTo",
      "probs": [0.1172, 0.4967, 0.212, 0.0967, 0.0773]
    },
    {
      "label": "JTo",
      "probs": [0.0849, 0.5293, 0.1953, 0.105, 0.0855]
    },
    {
      "label": "TT",
      "probs": [0.1116, 0.5157, 0.1979, 0.0993, 0.0755]
    },
    {
      "label": "T9s",
      "probs": [0.0795, 0.4855, 0.2234, 0.118, 0.0937]
    },
    {
      "label": "T8s",
      "probs": [0.0915, 0.5168, 0.191, 0.1098, 0.0908]
    },
    {
      "label": "T7s",
      "probs": [0.0876, 0.509, 0.2026, 0.1081, 0.0928]
    },
    {
      "label": "T6s",
      "probs": [0.088, 0.4871, 0.2052, 0.1219, 0.0977]
    },
    {
      "label": "T5s",
      "probs": [0.1462, 0.4741, 0.1809, 0.1019, 0.0969]
    },
    {
      "label": "T4s",
      "probs": [0.1216, 0.4843, 0.1801, 0.1165, 0.0976]
    },
    {
      "label": "T3s",
      "probs": [0.1676, 0.4851, 0.169, 0.0886, 0.0897]
    },
    {
      "label": "T2s",
      "probs": [0.2316, 0.4947, 0.1437, 0.069, 0.061]
    },
    {
      "label": "A9o",
      "probs": [0.0087, 0.4597, 0.2, 0.146, 0.1856]
    },
    {
      "label": "K9o",
      "probs": [0.0715, 0.5297, 0.2041, 0.1109, 0.0838]
    },
    {
      "label": "Q9o",
      "probs": [0.1716, 0.495, 0.171, 0.0851, 0.0774]
    },
    {
      "label": "J9o",
      "probs": [0.1412, 0.5654, 0.1455, 0.0805, 0.0674]
    },
    {
      "label": "T9o",
      "probs": [0.1527, 0.5201, 0.1623, 0.0863, 0.0786]
    },
    {
      "label": "99",
      "probs": [0.2659, 0.5359, 0.1037, 0.0521, 0.0424]
    },
    {
      "label": "98s",
      "probs": [0.1584, 0.5233, 0.1661, 0.0894, 0.0629]
    },
    {
      "label": "97s",
      "probs": [0.1388, 0.5181, 0.1829, 0.0886, 0.0717]
    },
    {
      "label": "96s",
      "probs": [0.1775, 0.524, 0.1558, 0.0853, 0.0573]
    },
    {
      "label": "95s",
      "probs": [0.2992, 0.491, 0.1142, 0.0497, 0.0459]
    },
    {
      "label": "94s",
      "probs": [0.2499, 0.5026, 0.124, 0.0739, 0.0497]
    },
    {
      "label": "93s",
      "probs": [0.333, 0.4673, 0.0967, 0.051, 0.0521]
    },
    {
      "label": "92s",
      "probs": [0.3491, 0.4685, 0.0962, 0.0446, 0.0416]
    },
    {
      "label": "A8o",
      "probs": [0.0151, 0.4537, 0.2151, 0.1515, 0.1645]
    },
    {
      "label": "K8o",
      "probs": [0.084, 0.5474, 0.1907, 0.1009, 0.077]
    },
    {
      "label": "Q8o",
      "probs": [0.2087, 0.5166, 0.1429, 0.0666, 0.0651]
    },
    {
      "label": "J8o",
      "probs": [0.1748, 0.5482, 0.1256, 0.0777, 0.0737]
    },
    {
      "label": "T8o",
      "probs": [0.1689, 0.5395, 0.1466, 0.075, 0.0701]
    },
    {
      "label": "98o",
      "probs": [0.3052, 0.517, 0.0897, 0.0451, 0.043]
    },
    {
      "label": "88",
      "probs": [0.2528, 0.5588, 0.0865, 0.0534, 0.0486]
    },
    {
      "label": "87s",
      "probs": [0.1217, 0.5478, 0.1583, 0.0893, 0.0829]
    },
    {
      "label": "86s",
      "probs": [0.1536, 0.5425, 0.1314, 0.0948, 0.0778]
    },
    {
      "label": "85s",
      "probs": [0.2649, 0.5303, 0.0916, 0.063, 0.0502]
    },
    {
      "label": "84s",
      "probs": [0.2609, 0.5315, 0.0912, 0.0675, 0.0489]
    },
    {
      "label": "83s",
      "probs": [0.3175, 0.498, 0.0812, 0.0541, 0.0493]
    },
    {
      "label": "82s",
      "probs": [0.3657, 0.4763, 0.0813, 0.0421, 0.0346]
    },
    {
      "label": "A7o",
      "probs": [0.0127, 0.4234, 0.2598, 0.1458, 0.1583]
    },
    {
      "label": "K7o",
      "probs": [0.1131, 0.559, 0.1759, 0.0812, 0.0707]
    },
    {
      "label": "Q7o",
      "probs": [0.2628, 0.4844, 0.1376, 0.0565, 0.0587]
    },
    {
      "label": "J7o",
      "probs": [0.2442, 0.5587, 0.1032, 0.0456, 0.0483]
    },
    {
      "label": "T7o",
      "probs": [0.2467, 0.4999, 0.1333, 0.0611, 0.059]
    },
    {
      "label": "97o",
      "probs": [0.3767, 0.4999, 0.0585, 0.0338, 0.0311]
    },
    {
      "label": "87o",
      "probs": [0.3631, 0.5, 0.0582, 0.0435, 0.0351]
    },
    {
      "label": "77",
      "probs": [0.319, 0.5195, 0.0808, 0.0367, 0.0441]
    },
    {
      "label": "76s",
      "probs": [0.1076, 0.5478, 0.1475, 0.1013, 0.0958]
    },
    {
      "label": "75s",
      "probs": [0.1776, 0.5486, 0.1217, 0.0791, 0.073]
    },
    {
      "label": "74s",
      "probs": [0.146, 0.5222, 0.1532, 0.0939, 0.0848]
    },
    {
      "label": "73s",
      "probs": [0.2546, 0.5172, 0.1048, 0.0569, 0.0665]
    },
    {
      "label": "72s",
      "probs": [0.3069, 0.5043, 0.1008, 0.0414, 0.0466]
    },
    {
      "label": "A6o",
      "probs": [0.0125, 0.4998, 0.1702, 0.1427, 0.1749]
    },
    {
      "label": "K6o",
      "probs": [0.0895, 0.5917, 0.1647, 0.0899, 0.0641]
    },
    {
      "label": "Q6o",
      "probs": [0.2923, 0.4932, 0.1124, 0.0544, 0.0477]
    },
    {
      "label": "J6o",
      "probs": [0.2633, 0.5658, 0.0908, 0.0445, 0.0355]
    },
    {
      "label": "T6o",
      "probs": [0.273, 0.5334, 0.0949, 0.0539, 0.0447]
    },
    {
      "label": "96o",
      "probs": [0.3411, 0.5079, 0.076, 0.0415, 0.0334]
    },
    {
      "label": "86o",
      "probs": [0.3361, 0.5374, 0.0531, 0.0439, 0.0295]
    },
    {
      "label": "76o",
      "probs": [0.2573, 0.5775, 0.0784, 0.0401, 0.0467]
    },
    {
      "label": "66",
      "probs": [0.2794, 0.5738, 0.0593, 0.0478, 0.0398]
    },
    {
      "label": "65s",
      "probs": [0.1804, 0.5686, 0.0987, 0.0825, 0.0698]
    },
    {
      "label": "64s",
      "probs": [0.1509, 0.5308, 0.1324, 0.102, 0.084]
    },
    {
      "label": "63s",
      "probs": [0.2911, 0.5156, 0.0844, 0.0533, 0.0557]
    },
    {
      "label": "62s",
      "probs": [0.2593, 0.5211, 0.1095, 0.0565, 0.0537]
    },
    {
      "label": "A5o",
      "probs": [0.0063, 0.4518, 0.1936, 0.1532, 0.1951]
    },
    {
      "label": "K5o",
      "probs": [0.0912, 0.5749, 0.1773, 0.088, 0.0687]
    },
    {
      "label": "Q5o",
      "probs": [0.3406, 0.4461, 0.1188, 0.0493, 0.0453]
    },
    {
      "label": "J5o",
      "probs": [0.306, 0.5115, 0.0934, 0.0463, 0.0428]
    },
    {
      "label": "T5o",
      "probs": [0.2426, 0.5422, 0.1153, 0.0513, 0.0486]
    },
    {
      "label": "95o",
      "probs": [0.3939, 0.4785, 0.0685, 0.0328, 0.0263]
    },
    {
      "label": "85o",
      "probs": [0.3591, 0.5133, 0.0609, 0.0389, 0.0278]
    },
    {
      "label": "75o",
      "probs": [0.2981, 0.5496, 0.0677, 0.0351, 0.0496]
    },
    {
      "label": "65o",
      "probs": [0.273, 0.5514, 0.0788, 0.0504, 0.0463]
    },
    {
      "label": "55",
      "probs": [0.5032, 0.4076, 0.0365, 0.0288, 0.0239]
    },
    {
      "label": "54s",
      "probs": [0.2045, 0.5788, 0.083, 0.0723, 0.0615]
    },
    {
      "label": "53s",
      "probs": [0.3267, 0.5152, 0.0601, 0.0452, 0.0528]
    },
    {
      "label": "52s",
      "probs": [0.4169, 0.4716, 0.0527, 0.03, 0.0289]
    },
    {
      "label": "A4o",
      "probs": [0.0261, 0.5268, 0.2241, 0.115, 0.108]
    },
    {
      "label": "K4o",
      "probs": [0.1361, 0.5459, 0.1808, 0.0778, 0.0594]
    },
    {
      "label": "Q4o",
      "probs": [0.4309, 0.4146, 0.0916, 0.0271, 0.0358]
    },
    {
      "label": "J4o",
      "probs": [0.4009, 0.4428, 0.0909, 0.03, 0.0354]
    },
    {
      "label": "T4o",
      "probs": [0.3903, 0.4326, 0.1017, 0.0379, 0.0375]
    },
    {
      "label": "94o",
      "probs": [0.4898, 0.4017, 0.0578, 0.023, 0.0277]
    },
    {
      "label": "84o",
      "probs": [0.5014, 0.4035, 0.0446, 0.0273, 0.0232]
    },
    {
      "label": "74o",
      "probs": [0.4787, 0.4041, 0.0611, 0.0252, 0.0308]
    },
    {
      "label": "64o",
      "probs": [0.4398, 0.4415, 0.0579, 0.0316, 0.0293]
    },
    {
      "label": "54o",
      "probs": [0.6011, 0.3296, 0.0325, 0.0205, 0.0163]
    },
    {
      "label": "44",
      "probs": [0.4708, 0.4311, 0.047, 0.027, 0.0241]
    },
    {
      "label": "43s",
      "probs": [0.3045, 0.53, 0.0619, 0.0554, 0.0482]
    },
    {
      "label": "42s",
      "probs": [0.3158, 0.5122, 0.0807, 0.0471, 0.0442]
    },
    {
      "label": "A3o",
      "probs": [0.0288, 0.534, 0.1585, 0.1356, 0.1431]
    },
    {
      "label": "K3o",
      "probs": [0.1541, 0.5507, 0.1407, 0.0907, 0.0639]
    },
    {
      "label": "Q3o",
      "probs": [0.368, 0.481, 0.0859, 0.0351, 0.03]
    },
    {
      "label": "J3o",
      "probs": [0.403, 0.4666, 0.0714, 0.0356, 0.0234]
    },
    {
      "label": "T3o",
      "probs": [0.3523, 0.4807, 0.0924, 0.0416, 0.0329]
    },
    {
      "label": "93o",
      "probs": [0.481, 0.4161, 0.0539, 0.0271, 0.0219]
    },
    {
      "label": "83o",
      "probs": [0.4828, 0.4334, 0.036, 0.0289, 0.0188]
    },
    {
      "label": "73o",
      "probs": [0.4684, 0.436, 0.0505, 0.0229, 0.0222]
    },
    {
      "label": "63o",
      "probs": [0.4531, 0.4523, 0.0444, 0.0283, 0.022]
    },
    {
      "label": "53o",
      "probs": [0.6242, 0.3277, 0.0259, 0.0143, 0.0079]
    },
    {
      "label": "43o",
      "probs": [0.4888, 0.4343, 0.0335, 0.0244, 0.019]
    },
    {
      "label": "33",
      "probs": [0.5576, 0.3787, 0.0269, 0.019, 0.0179]
    },
    {
      "label": "32s",
      "probs": [0.4688, 0.435, 0.0399, 0.0273, 0.0289]
    },
    {
      "label": "A2o",
      "probs": [0.0417, 0.5524, 0.1687, 0.1224, 0.1148]
    },
    {
      "label": "K2o",
      "probs": [0.2243, 0.6009, 0.0851, 0.0506, 0.0391]
    },
    {
      "label": "Q2o",
      "probs": [0.443, 0.4527, 0.0584, 0.0248, 0.0211]
    },
    {
      "label": "J2o",
      "probs": [0.4656, 0.464, 0.0355, 0.0227, 0.0121]
    },
    {
      "label": "T2o",
      "probs": [0.4704, 0.4546, 0.0385, 0.0219, 0.0147]
    },
    {
      "label": "92o",
      "probs": [0.5501, 0.3783, 0.0341, 0.0206, 0.017]
    },
    {
      "label": "82o",
      "probs": [0.5174, 0.4179, 0.0283, 0.0232, 0.0131]
    },
    {
      "label": "72o",
      "probs": [0.5141, 0.4113, 0.0355, 0.0201, 0.0189]
    },
    {
      "label": "62o",
      "probs": [0.5482, 0.3926, 0.0266, 0.0211, 0.0114]
    },
    {
      "label": "52o",
      "probs": [0.7293, 0.2461, 0.0195, 0.0051, 0.0]
    },
    {
      "label": "42o",
      "probs": [0.622, 0.3336, 0.0218, 0.0139, 0.0088]
    },
    {
      "label": "32o",
      "probs": [0.7448, 0.2303, 0.0181, 0.0044, 0.0023]
    },
    {
      "label": "22",
      "probs": [0.7995, 0.1814, 0.0151, 0.0039, 0.0]
    }
  ]
}
